tests/test_mock_transport.py
tests/test_run.py
tests/test_unixsocket_transport_live.py
tests/base.py
tests/__init__.py
tests/data.py
tests/test_unixsocket_transport.py
tests/test_base_transport.py
errand_boy-0.3.9.dist-info/DESCRIPTION.rst
errand_boy-0.3.9.dist-info/RECORD
errand_boy-0.3.9.dist-info/metadata.json
errand_boy-0.3.9.dist-info/WHEEL
errand_boy-0.3.9.dist-info/pbr.json
errand_boy-0.3.9.dist-info/METADATA
errand_boy-0.3.9.dist-info/top_level.txt
errand_boy/constants.py
errand_boy/exceptions.py
errand_boy/run.py
errand_boy/__init__.py
errand_boy/transports/mock.py
errand_boy/transports/base.py
errand_boy/transports/__init__.py
errand_boy/transports/unixsocket.py
