Metadata-Version: 2.0
Name: errand-boy
Version: 0.3.9
Summary: Establish a connection to the errand-boy deamon to execute commands without the memory overhead incurred by os.fork().
Home-page: https://github.com/greyside/errand-boy
Author: Seán Hayes
Author-email: sean@seanhayes.name
License: BSD
Download-URL: https://github.com/greyside/errand-boy
Keywords: os fork process memory celery
Platform: UNKNOWN
Classifier: Development Status :: 3 - Alpha
Classifier: Intended Audience :: Developers
Classifier: Intended Audience :: System Administrators
Classifier: License :: OSI Approved :: BSD License
Classifier: Programming Language :: Python
Classifier: Topic :: Software Development :: Libraries
Classifier: Topic :: Software Development :: Libraries :: Python Modules
Requires-Dist: eventlet
Requires-Dist: six
